sentenceninja/__init__.py
sentenceninja-0.1.dist-info/LICENSE
sentenceninja-0.1.dist-info/METADATA
sentenceninja-0.1.dist-info/WHEEL
sentenceninja-0.1.dist-info/top_level.txt
sentenceninja-0.1.dist-info/RECORD
