Metadata-Version: 2.1
Name: sentenceninja
Version: 0.1
Summary: To split paragraphs into individual sentences
Home-page: https://github.com/iamarkaj/sentenceninja
Author: Arkajyoti Basak
Author-email: arkajbasak1211@gmail.com
License: MIT
Keywords: split sentences
Platform: UNKNOWN
Classifier: Topic :: Scientific/Engineering
Classifier: License :: OSI Approved :: MIT License
Classifier: Programming Language :: Python :: 3
